MANIFEST.in
README.rst
setup.py
disptrace/__init__.py
disptrace/utils.py
disptrace.egg-info/PKG-INFO
disptrace.egg-info/SOURCES.txt
disptrace.egg-info/dependency_links.txt
disptrace.egg-info/not-zip-safe
disptrace.egg-info/requires.txt
disptrace.egg-info/top_level.txt
disptrace/templates/beginstack.html
disptrace/templates/call.html
disptrace/templates/endstack.html
disptrace/templates/page.html
test/test_disptrace.py