Metadata-Version: 1.1
Name: disptrace
Version: 0.4
Summary: Generate Python trace log in HTML
Home-page: https://github.com/atsuoishimoto/disptrace
Author: Atsuo Ishimoto
Author-email: ishimoto@gembook.org
License: MIT License
Platform: UNKNOWN
Classifier: Intended Audience :: Developers
Classifier: License :: OSI Approved :: MIT License
Classifier: Programming Language :: Python
Classifier: Topic :: Software Development :: Libraries :: Python Modules
Classifier: Topic :: Software Development :: Debuggers
